{
    "frameName": "Rite",
    "patterns": [
        {
            "valenceText": "annotation id: sejong.56703",
            "examples": [
                {
                    "frameName": "Rite",
                    "denotations": [
                        {
                            "id": "1",
                            "span": {
                                "begin": 13,
                                "end": 19
                            },
                            "obj": "target"
                        }
                    ],
                    "text": "그는 언제나 불순분자를 제거시키기에 바빴다.",
                    "target": "제거시키기에",
                    "ko_annotation_id": "sejong.56703",
                    "relations": []
                }
            ]
        },
        {
            "valenceText": "annotation id: sejong.56704",
            "examples": [
                {
                    "frameName": "Rite",
                    "denotations": [
                        {
                            "id": "1",
                            "span": {
                                "begin": 12,
                                "end": 17
                            },
                            "obj": "target"
                        }
                    ],
                    "text": "볼록 튀어나온 부분을 제거해내자 보기가 훨씬 좋았다.",
                    "target": "제거해내자",
                    "ko_annotation_id": "sejong.56704",
                    "relations": []
                }
            ]
        }
    ],
    "frameID": 301,
    "ko_pos": "VV",
    "ko_lu": "제거시키다.v.Rite",
    "lu_id": 10891,
    "en_lus": [
        "circumcise.v.5500"
    ]
}