{
    "frameName": "Grinding",
    "patterns": [
        {
            "valenceText": "annotation id: sejong.64480",
            "examples": [
                {
                    "frameName": "Grinding",
                    "denotations": [
                        {
                            "id": "1",
                            "span": {
                                "begin": 12,
                                "end": 14
                            },
                            "obj": "target"
                        }
                    ],
                    "text": "할머니는 떡살을 곱게 빻아 송편을 빚으셨다.",
                    "target": "빻아",
                    "ko_annotation_id": "sejong.64480",
                    "relations": []
                }
            ]
        },
        {
            "valenceText": "annotation id: sejong.64481",
            "examples": [
                {
                    "frameName": "Grinding",
                    "denotations": [
                        {
                            "id": "1",
                            "span": {
                                "begin": 9,
                                "end": 13
                            },
                            "obj": "target"
                        }
                    ],
                    "text": "옛날에 밀가루를 빻으려면 어떻게 했는 줄 아니?.",
                    "target": "빻으려면",
                    "ko_annotation_id": "sejong.64481",
                    "relations": []
                }
            ]
        }
    ],
    "frameID": 351,
    "ko_pos": "VV",
    "ko_lu": "빻다.v.Grinding",
    "lu_id": 11195,
    "en_lus": [
        "pulverize.v.6110"
    ]
}