{
    "frameName": "Emanating",
    "patterns": [
        {
            "valenceText": "annotation id: sejong.56835",
            "examples": [
                {
                    "frameName": "Emanating",
                    "denotations": [
                        {
                            "id": "1",
                            "span": {
                                "begin": 22,
                                "end": 28
                            },
                            "obj": "target"
                        }
                    ],
                    "text": "예술가들은 인간의 내면 감정들을 외부로 표현시키려고 애를 쓰는 사람들이다.",
                    "target": "표현시키려고",
                    "ko_annotation_id": "sejong.56835",
                    "relations": []
                }
            ]
        },
        {
            "valenceText": "annotation id: sejong.56836",
            "examples": [
                {
                    "frameName": "Emanating",
                    "denotations": [
                        {
                            "id": "1",
                            "span": {
                                "begin": 43,
                                "end": 47
                            },
                            "obj": "target"
                        }
                    ],
                    "text": "이는 보색인 푸른색 계열을 차단시킴으로서 하늘색이나 바닷물색등 푸른색을 검게 표현시켜 준다.",
                    "target": "표현시켜",
                    "ko_annotation_id": "sejong.56836",
                    "relations": []
                }
            ]
        }
    ],
    "frameID": 361,
    "ko_pos": "VV",
    "ko_lu": "표현시키다.v.Emanating",
    "lu_id": 11261,
    "en_lus": [
        "exude.v.6255"
    ]
}