{
    "ko_pos": "NNG",
    "patterns": [
        {
            "examples": [
                {
                    "text": "미국기업연구소 선임 연구원인 Kristol 씨는 The Public Interest를 공동편집하고 The National Interest를 발행하고 있다.",
                    "relations": [
                        {
                            "subj": "1",
                            "obj": "2",
                            "pred": ""
                        }
                    ],
                    "annotation_id": 1395,
                    "sent_id": 258,
                    "frameName": "Origin",
                    "ko_annotation_id": 7358,
                    "origin_lus": [
                        "American"
                    ],
                    "denotations": [
                        {
                            "span": {
                                "begin": 0,
                                "end": 2
                            },
                            "obj": "target",
                            "id": "1"
                        },
                        {
                            "span": {
                                "begin": 2,
                                "end": 4
                            },
                            "obj": "entity",
                            "id": "2"
                        }
                    ]
                }
            ],
            "valenceText": "annotation id: 7358"
        }
    ],
    "frameName": "Origin",
    "lu_id": 2295,
    "frameID": 1103,
    "ko_lu": "미국.n.Origin",
    "en_lus": [
        "American"
    ]
}