{
    "frameName": "Destroying",
    "patterns": [
        {
            "valenceText": "annotation id: 8952",
            "examples": [
                {
                    "frameName": "Destroying",
                    "denotations": [
                        {
                            "obj": "cause",
                            "span": {
                                "begin": 32,
                                "end": 37
                            },
                            "id": "2"
                        },
                        {
                            "obj": "target",
                            "span": {
                                "begin": 39,
                                "end": 41
                            },
                            "id": "1"
                        }
                    ],
                    "origin_lus": [
                        "devastation"
                    ],
                    "ko_annotation_id": 8952,
                    "text": "이라크는 전쟁 종료 이후 경제적 제재 하에 있었고, 이는 폭격 작전의 황폐로부터 회복하기 위한 나라의 능력을 좌절시켰다고 누군가가 말하고 있다.",
                    "sent_id": 1486,
                    "relations": [
                        {
                            "subj": "1",
                            "obj": "2",
                            "pred": ""
                        }
                    ],
                    "annotation_id": 7048
                }
            ]
        },
        {
            "valenceText": "annotation id: sejong.42442",
            "examples": [
                {
                    "frameName": "Destroying",
                    "denotations": [
                        {
                            "obj": "target",
                            "span": {
                                "begin": 6,
                                "end": 8
                            },
                            "id": "1"
                        }
                    ],
                    "text": "인간정신의 황폐가 극에 달하고 있다.",
                    "target": "황폐",
                    "ko_annotation_id": "sejong.42442",
                    "relations": []
                }
            ]
        }
    ],
    "frameID": 417,
    "ko_pos": "NNG",
    "ko_lu": "황폐.n.Destroying",
    "lu_id": 2740,
    "en_lus": [
        "devastation"
    ]
}