{
    "ko_lu": "결혼.n",
    "patterns": [
        {
            "valenceText": "annotation id: 9806",
            "examples": {
                "ko_annotation_id": 9806,
                "denotations": [
                    {
                        "obj": "partner_1",
                        "span": {
                            "begin": 20,
                            "end": 21
                        },
                        "id": "2"
                    },
                    {
                        "obj": "target",
                        "span": {
                            "begin": 23,
                            "end": 25
                        },
                        "id": "1"
                    }
                ],
                "frameName": "Personal_relationship",
                "origin_lus": [
                    "marriage"
                ],
                "relations": [
                    {
                        "pred": "",
                        "obj": "2",
                        "subj": "1"
                    }
                ],
                "annotation_id": 5352,
                "sent_id": 1021
            }
        }
    ],
    "frameID": 102,
    "en_lu": [
        "marriage"
    ],
    "ko_pos": "NNG",
    "frameName": "Personal_relationship"
}