{
    "frameName": "Cognitive_connection",
    "patterns": [
        {
            "valenceText": "annotation id: 12296",
            "examples": [
                {
                    "frameName": "Cognitive_connection",
                    "denotations": [
                        {
                            "obj": "concept_2",
                            "span": {
                                "begin": 75,
                                "end": 79
                            },
                            "id": "3"
                        },
                        {
                            "obj": "target",
                            "span": {
                                "begin": 113,
                                "end": 115
                            },
                            "id": "1"
                        },
                        {
                            "obj": "concept_1",
                            "span": {
                                "begin": 116,
                                "end": 118
                            },
                            "id": "2"
                        }
                    ],
                    "origin_lus": [
                        "related",
                        "associated",
                        "kanren .関連 ",
                        "kankee .関係 "
                    ],
                    "ko_annotation_id": 12296,
                    "text": "중국은 지속적으로 생물 및 독소 무기 금지조약을 준수하겠다고 공개적으로 선언하였지만, 과거 미국 정부 보고서는 중국이 소규모의 공격용 생물무기 프로그램을 가지고 있을 뿐만 아니라, 또한 통제된 생물무기 관련 품목을 이란과 같은 확산 우려가 있는 국가들에 이전하였다고 추정하였다.",
                    "sent_id": 2112,
                    "relations": [
                        {
                            "subj": "1",
                            "obj": "2",
                            "pred": ""
                        },
                        {
                            "subj": "1",
                            "obj": "3",
                            "pred": ""
                        }
                    ],
                    "annotation_id": 10445
                }
            ]
        },
        {
            "valenceText": "annotation id: 12297",
            "examples": [
                {
                    "frameName": "Cognitive_connection",
                    "denotations": [
                        {
                            "obj": "concept_2",
                            "span": {
                                "begin": 26,
                                "end": 30
                            },
                            "id": "2"
                        },
                        {
                            "obj": "target",
                            "span": {
                                "begin": 31,
                                "end": 33
                            },
                            "id": "1"
                        },
                        {
                            "obj": "concept_1",
                            "span": {
                                "begin": 34,
                                "end": 42
                            },
                            "id": "3"
                        }
                    ],
                    "origin_lus": [
                        "related",
                        "associated",
                        "kanren .関連 ",
                        "kankee .関係 "
                    ],
                    "ko_annotation_id": 12297,
                    "text": "1997년에, 추가의 중국 회사 2개가 이란에 화학무기 관련 전구물질과 장비를 판매하여 미 국무성의 제재를 받았다.",
                    "sent_id": 2256,
                    "relations": [
                        {
                            "subj": "1",
                            "obj": "2",
                            "pred": ""
                        },
                        {
                            "subj": "1",
                            "obj": "3",
                            "pred": ""
                        }
                    ],
                    "annotation_id": 11297
                }
            ]
        },
        {
            "valenceText": "annotation id: 12298",
            "examples": [
                {
                    "frameName": "Cognitive_connection",
                    "denotations": [
                        {
                            "obj": "concept_2",
                            "span": {
                                "begin": 62,
                                "end": 65
                            },
                            "id": "2"
                        },
                        {
                            "obj": "target",
                            "span": {
                                "begin": 66,
                                "end": 68
                            },
                            "id": "1"
                        },
                        {
                            "obj": "concept_1",
                            "span": {
                                "begin": 69,
                                "end": 71
                            },
                            "id": "3"
                        }
                    ],
                    "origin_lus": [
                        "related",
                        "associated",
                        "kanren .関連 ",
                        "kankee .関係 "
                    ],
                    "ko_annotation_id": 12298,
                    "text": "이란은 모든 측면의 화학무기 프로그램을 위한 독자적인 생산 능력을 갖추기 위한 혼신의 노력을 하고 있을지라도, 화학전 관련 기술을 위해 외국 자원에 의존하는데 머물고 있다.",
                    "sent_id": 3345,
                    "relations": [
                        {
                            "subj": "1",
                            "obj": "2",
                            "pred": ""
                        },
                        {
                            "subj": "1",
                            "obj": "3",
                            "pred": ""
                        }
                    ],
                    "annotation_id": 17761
                }
            ]
        },
        {
            "valenceText": "annotation id: 12299",
            "examples": [
                {
                    "frameName": "Cognitive_connection",
                    "denotations": [
                        {
                            "obj": "concept_2",
                            "span": {
                                "begin": 20,
                                "end": 21
                            },
                            "id": "2"
                        },
                        {
                            "obj": "target",
                            "span": {
                                "begin": 22,
                                "end": 24
                            },
                            "id": "1"
                        },
                        {
                            "obj": "concept_1",
                            "span": {
                                "begin": 25,
                                "end": 27
                            },
                            "id": "3"
                        }
                    ],
                    "origin_lus": [
                        "related",
                        "associated",
                        "kanren .関連 ",
                        "kankee .関係 "
                    ],
                    "ko_annotation_id": 12299,
                    "text": "벨기에 신문은 벨기에가 이란인들에게 핵 관련 훈련을 제공하였다고 주장한다. ( 2455 ).",
                    "sent_id": 3401,
                    "relations": [
                        {
                            "subj": "1",
                            "obj": "2",
                            "pred": ""
                        },
                        {
                            "subj": "1",
                            "obj": "3",
                            "pred": ""
                        }
                    ],
                    "annotation_id": 17993
                }
            ]
        },
        {
            "valenceText": "annotation id: 12300",
            "examples": [
                {
                    "frameName": "Cognitive_connection",
                    "denotations": [
                        {
                            "obj": "concept_2",
                            "span": {
                                "begin": 16,
                                "end": 17
                            },
                            "id": "3"
                        },
                        {
                            "obj": "target",
                            "span": {
                                "begin": 18,
                                "end": 20
                            },
                            "id": "1"
                        },
                        {
                            "obj": "concept_1",
                            "span": {
                                "begin": 21,
                                "end": 27
                            },
                            "id": "2"
                        }
                    ],
                    "origin_lus": [
                        "related",
                        "associated",
                        "kanren .関連 ",
                        "kankee .関係 "
                    ],
                    "ko_annotation_id": 12300,
                    "text": "이란은 아르헨티나로부터 다른 핵 관련 지원과 재료를 수령하였을 것이다 ( 6883, 6897 ).",
                    "sent_id": 3476,
                    "relations": [
                        {
                            "subj": "1",
                            "obj": "2",
                            "pred": ""
                        },
                        {
                            "subj": "1",
                            "obj": "3",
                            "pred": ""
                        }
                    ],
                    "annotation_id": 0
                }
            ]
        },
        {
            "valenceText": "annotation id: 12301",
            "examples": [
                {
                    "frameName": "Cognitive_connection",
                    "denotations": [
                        {
                            "obj": "target",
                            "span": {
                                "begin": 39,
                                "end": 41
                            },
                            "id": "1"
                        },
                        {
                            "obj": "concept_1",
                            "span": {
                                "begin": 42,
                                "end": 51
                            },
                            "id": "2"
                        }
                    ],
                    "origin_lus": [
                        "related",
                        "associated",
                        "kanren .関連 ",
                        "kankee .関係 "
                    ],
                    "ko_annotation_id": 12301,
                    "text": "중국의 대 위성 ( ASAT ) 능력의 개발은 또한 중국의 미사일 및 관련 군 우주 프로그램에 대한 우려를 불러왔다.",
                    "sent_id": 2130,
                    "relations": [
                        {
                            "subj": "1",
                            "obj": "2",
                            "pred": ""
                        }
                    ],
                    "annotation_id": 10607
                }
            ]
        },
        {
            "valenceText": "annotation id: 12302",
            "examples": [
                {
                    "frameName": "Cognitive_connection",
                    "denotations": [
                        {
                            "obj": "target",
                            "span": {
                                "begin": 42,
                                "end": 44
                            },
                            "id": "1"
                        },
                        {
                            "obj": "concept_1",
                            "span": {
                                "begin": 45,
                                "end": 47
                            },
                            "id": "2"
                        }
                    ],
                    "origin_lus": [
                        "related",
                        "associated",
                        "kanren .関連 ",
                        "kankee .関係 "
                    ],
                    "ko_annotation_id": 12302,
                    "text": "그러나, 카자흐스탄 대통령 Nazarbayev는 카자흐스탄의 생물 무기 및 관련 기술의 비확산에 대한 약속을 선언하였다.",
                    "sent_id": 2683,
                    "relations": [
                        {
                            "subj": "1",
                            "obj": "2",
                            "pred": ""
                        }
                    ],
                    "annotation_id": 13444
                }
            ]
        },
        {
            "valenceText": "annotation id: 12303",
            "examples": [
                {
                    "frameName": "Cognitive_connection",
                    "denotations": [
                        {
                            "obj": "concept_2",
                            "span": {
                                "begin": 18,
                                "end": 23
                            },
                            "id": "3"
                        },
                        {
                            "obj": "target",
                            "span": {
                                "begin": 62,
                                "end": 64
                            },
                            "id": "1"
                        },
                        {
                            "obj": "concept_1",
                            "span": {
                                "begin": 65,
                                "end": 67
                            },
                            "id": "2"
                        }
                    ],
                    "origin_lus": [
                        "related",
                        "associated",
                        "kanren .関連 ",
                        "kankee .関係 "
                    ],
                    "ko_annotation_id": 12303,
                    "text": "1997년 1월에, 이란은 이란 생명 공학 협회 ( IBS ) 라 불리는 조직을 만들었는데, 이것은 생명 공학 관련 연구에 중점을 두는 여러 연구소와 개인들을 함께 가져오는 통솔 기구로서의 역할을 한다.",
                    "sent_id": 2170,
                    "relations": [
                        {
                            "subj": "1",
                            "obj": "2",
                            "pred": ""
                        },
                        {
                            "subj": "1",
                            "obj": "3",
                            "pred": ""
                        }
                    ],
                    "annotation_id": 10813
                }
            ]
        },
        {
            "valenceText": "annotation id: 12304",
            "examples": [
                {
                    "frameName": "Cognitive_connection",
                    "denotations": [
                        {
                            "obj": "concept_2",
                            "span": {
                                "begin": 19,
                                "end": 23
                            },
                            "id": "2"
                        },
                        {
                            "obj": "target",
                            "span": {
                                "begin": 24,
                                "end": 26
                            },
                            "id": "1"
                        },
                        {
                            "obj": "concept_1",
                            "span": {
                                "begin": 27,
                                "end": 29
                            },
                            "id": "3"
                        }
                    ],
                    "origin_lus": [
                        "related",
                        "associated",
                        "kanren .関連 ",
                        "kankee .関係 "
                    ],
                    "ko_annotation_id": 12304,
                    "text": "이란의 정교한 연구 시설들은 불법 생물무기 관련 활동을 위한 위장으로서의 역할을 하고 군민 양용 물질을 수입하기 위한 합법적인 변명을 제공할 수 있다.",
                    "sent_id": 2181,
                    "relations": [
                        {
                            "subj": "1",
                            "obj": "2",
                            "pred": ""
                        },
                        {
                            "subj": "1",
                            "obj": "3",
                            "pred": ""
                        }
                    ],
                    "annotation_id": 10866
                }
            ]
        },
        {
            "valenceText": "annotation id: 12305",
            "examples": [
                {
                    "frameName": "Cognitive_connection",
                    "denotations": [
                        {
                            "obj": "concept_2",
                            "span": {
                                "begin": 4,
                                "end": 7
                            },
                            "id": "2"
                        },
                        {
                            "obj": "target",
                            "span": {
                                "begin": 13,
                                "end": 15
                            },
                            "id": "1"
                        },
                        {
                            "obj": "concept_1",
                            "span": {
                                "begin": 16,
                                "end": 18
                            },
                            "id": "3"
                        }
                    ],
                    "origin_lus": [
                        "related",
                        "associated",
                        "kanren .関連 ",
                        "kankee .関係 "
                    ],
                    "ko_annotation_id": 12305,
                    "text": "확보한 미사일과 미사일 관련 기술의 양과 질, 고유의 미사일 관련 인력의 크기와 경력.",
                    "sent_id": 2406,
                    "relations": [
                        {
                            "subj": "1",
                            "obj": "2",
                            "pred": ""
                        },
                        {
                            "subj": "1",
                            "obj": "3",
                            "pred": ""
                        }
                    ],
                    "annotation_id": 12133
                }
            ]
        },
        {
            "valenceText": "annotation id: 12306",
            "examples": [
                {
                    "frameName": "Cognitive_connection",
                    "denotations": [
                        {
                            "obj": "concept_2",
                            "span": {
                                "begin": 21,
                                "end": 24
                            },
                            "id": "2"
                        },
                        {
                            "obj": "target",
                            "span": {
                                "begin": 25,
                                "end": 27
                            },
                            "id": "1"
                        },
                        {
                            "obj": "concept_1",
                            "span": {
                                "begin": 28,
                                "end": 30
                            },
                            "id": "3"
                        }
                    ],
                    "origin_lus": [
                        "related",
                        "associated",
                        "kanren .関連 ",
                        "kankee .関係 "
                    ],
                    "ko_annotation_id": 12306,
                    "text": "특히, 중국 방문 동안, 그는 다음의 미사일 관련 분야에서 중국의 동의를 확보하였다 : 1986년부터 HY-1 silkworm 과 HY-2 seercuker 해안 방어 미사일 인도와 이들 미사일의 조립 시설 설립 지원.",
                    "sent_id": 2448,
                    "relations": [
                        {
                            "subj": "1",
                            "obj": "2",
                            "pred": ""
                        },
                        {
                            "subj": "1",
                            "obj": "3",
                            "pred": ""
                        }
                    ],
                    "annotation_id": 12310
                }
            ]
        },
        {
            "valenceText": "annotation id: 12307",
            "examples": [
                {
                    "frameName": "Cognitive_connection",
                    "denotations": [
                        {
                            "obj": "concept_2",
                            "span": {
                                "begin": 24,
                                "end": 27
                            },
                            "id": "2"
                        },
                        {
                            "obj": "target",
                            "span": {
                                "begin": 28,
                                "end": 30
                            },
                            "id": "1"
                        },
                        {
                            "obj": "concept_1",
                            "span": {
                                "begin": 31,
                                "end": 33
                            },
                            "id": "3"
                        }
                    ],
                    "origin_lus": [
                        "related",
                        "associated",
                        "kanren .関連 ",
                        "kankee .関係 "
                    ],
                    "ko_annotation_id": 12307,
                    "text": "북한 방문은 똑같이 유익하였고, 그는 다음 미사일 관련 분야에서 북한의 지원을 확보하였다 : HN-5A SAM 인도 및 이들과 HQ-q/2 SAMs을 위한 조립 시설 건설에서의 지원.",
                    "sent_id": 2450,
                    "relations": [
                        {
                            "subj": "1",
                            "obj": "2",
                            "pred": ""
                        },
                        {
                            "subj": "1",
                            "obj": "3",
                            "pred": ""
                        }
                    ],
                    "annotation_id": 12325
                }
            ]
        },
        {
            "valenceText": "annotation id: 12308",
            "examples": [
                {
                    "frameName": "Cognitive_connection",
                    "denotations": [
                        {
                            "obj": "concept_2",
                            "span": {
                                "begin": 34,
                                "end": 37
                            },
                            "id": "2"
                        },
                        {
                            "obj": "target",
                            "span": {
                                "begin": 43,
                                "end": 45
                            },
                            "id": "1"
                        },
                        {
                            "obj": "concept_1",
                            "span": {
                                "begin": 46,
                                "end": 48
                            },
                            "id": "3"
                        }
                    ],
                    "origin_lus": [
                        "related",
                        "associated",
                        "kanren .関連 ",
                        "kankee .関係 "
                    ],
                    "ko_annotation_id": 12308,
                    "text": "다른 국가들 ( 예, 북한, 리비아, 그리고 시리아 ) 에서 미사일과 미사일 관련 기술의 개발을 재정 지원하기 위한 이란의 지속적인 능력과 의지.",
                    "sent_id": 2541,
                    "relations": [
                        {
                            "subj": "1",
                            "obj": "2",
                            "pred": ""
                        },
                        {
                            "subj": "1",
                            "obj": "3",
                            "pred": ""
                        }
                    ],
                    "annotation_id": 12685
                }
            ]
        },
        {
            "valenceText": "annotation id: 12309",
            "examples": [
                {
                    "frameName": "Cognitive_connection",
                    "denotations": [
                        {
                            "obj": "concept_2",
                            "span": {
                                "begin": 17,
                                "end": 20
                            },
                            "id": "2"
                        },
                        {
                            "obj": "target",
                            "span": {
                                "begin": 21,
                                "end": 23
                            },
                            "id": "1"
                        },
                        {
                            "obj": "concept_1",
                            "span": {
                                "begin": 24,
                                "end": 26
                            },
                            "id": "3"
                        }
                    ],
                    "origin_lus": [
                        "related",
                        "associated",
                        "kanren .関連 ",
                        "kankee .関係 "
                    ],
                    "ko_annotation_id": 12309,
                    "text": "그런 다음 리비아는 자국 내의 핵무기 관련 활동의 제거를 입증하기 위해 국제 원자력 기구를 초청하였다.",
                    "sent_id": 2701,
                    "relations": [
                        {
                            "subj": "1",
                            "obj": "2",
                            "pred": ""
                        },
                        {
                            "subj": "1",
                            "obj": "3",
                            "pred": ""
                        }
                    ],
                    "annotation_id": 13543
                }
            ]
        },
        {
            "valenceText": "annotation id: 12310",
            "examples": [
                {
                    "frameName": "Cognitive_connection",
                    "denotations": [
                        {
                            "obj": "target",
                            "span": {
                                "begin": 37,
                                "end": 39
                            },
                            "id": "1"
                        },
                        {
                            "obj": "concepts",
                            "span": {
                                "begin": 40,
                                "end": 42
                            },
                            "id": "2"
                        }
                    ],
                    "origin_lus": [
                        "related",
                        "associated",
                        "kanren .関連 ",
                        "kankee .関係 "
                    ],
                    "ko_annotation_id": 12310,
                    "text": "2004년 4월에, 이란은 농축 프로그램을 보류하였을 뿐만 아니라 관련 부품을 생산하고 조립하는 것도 멈추었다고 부언하며, IAEA와의 협력 관계를 증진시키겠다고 맹세하였다.",
                    "sent_id": 2370,
                    "relations": [
                        {
                            "subj": "1",
                            "obj": "2",
                            "pred": ""
                        }
                    ],
                    "annotation_id": 11955
                }
            ]
        },
        {
            "valenceText": "annotation id: 12311",
            "examples": [
                {
                    "frameName": "Cognitive_connection",
                    "denotations": [
                        {
                            "obj": "target",
                            "span": {
                                "begin": 26,
                                "end": 28
                            },
                            "id": "1"
                        },
                        {
                            "obj": "concept_1",
                            "span": {
                                "begin": 29,
                                "end": 31
                            },
                            "id": "2"
                        }
                    ],
                    "origin_lus": [
                        "related",
                        "associated",
                        "kanren .関連 ",
                        "kankee .関係 "
                    ],
                    "ko_annotation_id": 12311,
                    "text": "협정에 따라, 북한은 가스 흑연 감속 원자로와 관련 시설을 동결하고, 그렇게 동결한 것을 IAEA가 감시하도록 허용하는 것에 동의하였다.",
                    "sent_id": 2961,
                    "relations": [
                        {
                            "subj": "1",
                            "obj": "2",
                            "pred": ""
                        }
                    ],
                    "annotation_id": 15228
                }
            ]
        },
        {
            "valenceText": "annotation id: 12312",
            "examples": [
                {
                    "frameName": "Cognitive_connection",
                    "denotations": [
                        {
                            "obj": "target",
                            "span": {
                                "begin": 60,
                                "end": 62
                            },
                            "id": "1"
                        },
                        {
                            "obj": "concept_1",
                            "span": {
                                "begin": 63,
                                "end": 68
                            },
                            "id": "2"
                        }
                    ],
                    "origin_lus": [
                        "related",
                        "associated",
                        "kanren .関連 ",
                        "kankee .関係 "
                    ],
                    "ko_annotation_id": 12312,
                    "text": "인종 격리 정책을 끝내기 위한 결정과 병행하여, 정부는 1989년에 폭탄 프로그램을 중단하였고 기존 무기와 관련 생산 장비를 해체하였다.",
                    "sent_id": 3022,
                    "relations": [
                        {
                            "subj": "1",
                            "obj": "2",
                            "pred": ""
                        }
                    ],
                    "annotation_id": 15602
                }
            ]
        },
        {
            "valenceText": "annotation id: 12313",
            "examples": [
                {
                    "frameName": "Cognitive_connection",
                    "denotations": [
                        {
                            "obj": "Concept_1",
                            "span": {
                                "begin": 4,
                                "end": 14
                            }
                        },
                        {
                            "obj": "Concept_2",
                            "span": {
                                "begin": 17,
                                "end": 19
                            }
                        },
                        {
                            "obj": "Target",
                            "span": {
                                "begin": 17,
                                "end": 19
                            }
                        }
                    ],
                    "origin_lus": [
                        "related",
                        "associated",
                        "kanren .関連 ",
                        "kankee .関係 "
                    ],
                    "ko_annotation_id": 12313,
                    "text": "각지에 「뇌 외상 친우회」 및 관련 단체가 결성되어 가는 가운데, 가족 단체의 권고로 장애 연금, 장애인 수첩의 취득률도 오르고 있어, 작년의 해당 단체의 조사에 따르면, 장애인 수첩을 가지고 있지 않은 사람은 약 20%로 나타났다.",
                    "sent_id": 4112,
                    "relations": [],
                    "annotation_id": 0
                }
            ]
        },
        {
            "valenceText": "annotation id: 12314",
            "examples": [
                {
                    "frameName": "Cognitive_connection",
                    "denotations": [
                        {
                            "obj": "Concept_1",
                            "span": {
                                "begin": 3,
                                "end": 5
                            }
                        },
                        {
                            "obj": "Concept_2",
                            "span": {
                                "begin": 6,
                                "end": 13
                            }
                        },
                        {
                            "obj": "Target",
                            "span": {
                                "begin": 16,
                                "end": 18
                            }
                        }
                    ],
                    "origin_lus": [
                        "related",
                        "associated",
                        "kanren .関連 ",
                        "kankee .関係 "
                    ],
                    "ko_annotation_id": 12314,
                    "text": "(이 또한 시크 성능 등과도 관련이 있으므로 엄밀히 말하면 다르다).",
                    "sent_id": 4341,
                    "relations": [],
                    "annotation_id": 0
                }
            ]
        },
        {
            "valenceText": "annotation id: 12315",
            "examples": [
                {
                    "frameName": "Cognitive_connection",
                    "denotations": [
                        {
                            "obj": "Concept_1",
                            "span": {
                                "begin": 20,
                                "end": 22
                            }
                        },
                        {
                            "obj": "Target",
                            "span": {
                                "begin": 24,
                                "end": 26
                            }
                        }
                    ],
                    "origin_lus": [
                        "related",
                        "associated",
                        "kanren .関連 ",
                        "kankee .関係 "
                    ],
                    "ko_annotation_id": 12315,
                    "text": "스카이프 영어판을 사용하고 있는데, 그것과 관련이 있는 모양입니다.",
                    "sent_id": 3918,
                    "relations": [],
                    "annotation_id": 0
                }
            ]
        },
        {
            "valenceText": "annotation id: 12316",
            "examples": [
                {
                    "frameName": "Cognitive_connection",
                    "denotations": [
                        {
                            "obj": "Concept_1",
                            "span": {
                                "begin": 2,
                                "end": 10
                            }
                        },
                        {
                            "obj": "Target",
                            "span": {
                                "begin": 13,
                                "end": 15
                            }
                        }
                    ],
                    "origin_lus": [
                        "related",
                        "associated",
                        "kanren .関連 ",
                        "kankee .関係 "
                    ],
                    "ko_annotation_id": 12316,
                    "text": "제 나이가 어린 것과도 관련이 있을지도 모릅니다.",
                    "sent_id": 4319,
                    "relations": [],
                    "annotation_id": 0
                }
            ]
        },
        {
            "valenceText": "annotation id: sejong.41412",
            "examples": [
                {
                    "frameName": "Cognitive_connection",
                    "denotations": [
                        {
                            "obj": "target",
                            "span": {
                                "begin": 14,
                                "end": 16
                            },
                            "id": "1"
                        }
                    ],
                    "text": "이번 일은 나와는 아무런 관련이 없다.경찰은 그와 밀접한 관련을 맺고 있는 몇 사람을 소환하여 조사하기로 했다.",
                    "target": "관련",
                    "ko_annotation_id": "sejong.41412",
                    "relations": []
                }
            ]
        }
    ],
    "frameID": 720,
    "ko_pos": "NNG",
    "ko_lu": "관련.n.Cognitive_connection",
    "lu_id": 3600,
    "en_lus": [
        "associated",
        "relate",
        "kanren .関連 ",
        "kankee .関係 "
    ]
}