{
    "ko_lu": "숲.n.Biological_area",
    "lu_id": 4580,
    "frameID": 193,
    "en_lus": [
        "mori .森 "
    ],
    "ko_pos": "NNG",
    "patterns": [
        {
            "valenceText": "annotation id: 15603",
            "examples": [
                {
                    "denotations": [
                        {
                            "obj": "Locale",
                            "span": {
                                "begin": 62,
                                "end": 63
                            }
                        },
                        {
                            "obj": "Target",
                            "span": {
                                "begin": 62,
                                "end": 63
                            }
                        }
                    ],
                    "frameName": "Biological_area",
                    "text": "1 신칸센 창문 너머로 펼쳐지는, 수확이 끝난 밭의 끝없는 풍경을 바라보면서, 어느새 그곳에 있었을 천년 전의 숲을 상상하고 있다.",
                    "relations": [],
                    "sent_id": 4760,
                    "ko_annotation_id": 15603,
                    "origin_lus": [
                        "mori .森 "
                    ],
                    "annotation_id": 0
                }
            ]
        },
        {
            "valenceText": "annotation id: 15604",
            "examples": [
                {
                    "denotations": [
                        {
                            "obj": "Locale",
                            "span": {
                                "begin": 9,
                                "end": 10
                            }
                        },
                        {
                            "obj": "Target",
                            "span": {
                                "begin": 9,
                                "end": 10
                            }
                        }
                    ],
                    "frameName": "Biological_area",
                    "text": "자연계를 보면, 숲과 바다, 강, 대지, 어디를 가든 크고 작은 각양각색의 동식물이 공존관계를 이루며 존재하듯이, 인터넷상에서도, 고객, 제조회사, 서플라이어, 유통기업 등이 단계의 차이를 뛰어넘어 하나의 구성원으로서 공존하고, 진화해간다.",
                    "relations": [],
                    "sent_id": 3611,
                    "ko_annotation_id": 15604,
                    "origin_lus": [
                        "mori .森 "
                    ],
                    "annotation_id": 0
                }
            ]
        },
        {
            "valenceText": "annotation id: 15605",
            "examples": [
                {
                    "denotations": [
                        {
                            "obj": "Relative_location",
                            "span": {
                                "begin": 5,
                                "end": 9
                            }
                        },
                        {
                            "obj": "Locale",
                            "span": {
                                "begin": 11,
                                "end": 12
                            }
                        },
                        {
                            "obj": "Target",
                            "span": {
                                "begin": 11,
                                "end": 12
                            }
                        }
                    ],
                    "frameName": "Biological_area",
                    "text": "그런데, 이 신사의 숲에는 말이지, 오래 전부터, 여우 모자가 살고 있었대.",
                    "relations": [],
                    "sent_id": 3705,
                    "ko_annotation_id": 15605,
                    "origin_lus": [
                        "mori .森 "
                    ],
                    "annotation_id": 0
                }
            ]
        },
        {
            "valenceText": "annotation id: sejong.14284",
            "examples": [
                {
                    "denotations": [
                        {
                            "obj": "target",
                            "id": "1",
                            "span": {
                                "begin": 31,
                                "end": 32
                            }
                        }
                    ],
                    "text": "나무 몇 그루 없던 곳이었는데 비가 오자 어느새 울창한 숲을 이루었다.",
                    "relations": [],
                    "target": "숲",
                    "ko_annotation_id": "sejong.14284",
                    "frameName": "Biological_area"
                }
            ]
        },
        {
            "valenceText": "annotation id: sejong.14285",
            "examples": [
                {
                    "denotations": [
                        {
                            "obj": "target",
                            "id": "1",
                            "span": {
                                "begin": 0,
                                "end": 1
                            }
                        }
                    ],
                    "text": "숲이 울창해야 큰비가 와도 문제가 생기지 않는다.",
                    "relations": [],
                    "target": "숲",
                    "ko_annotation_id": "sejong.14285",
                    "frameName": "Biological_area"
                }
            ]
        }
    ],
    "frameName": "Biological_area"
}