{
    "ko_lu": "이기다.v",
    "patterns": [
        {
            "valenceText": "annotation id: 17026",
            "examples": {
                "ko_annotation_id": 17026,
                "denotations": [
                    {
                        "obj": "Competitor",
                        "span": {
                            "begin": 0,
                            "end": 5
                        }
                    },
                    {
                        "obj": "Competition",
                        "span": {
                            "begin": 7,
                            "end": 15
                        }
                    },
                    {
                        "obj": "Opponent",
                        "span": {
                            "begin": 18,
                            "end": 24
                        }
                    },
                    {
                        "obj": "Target",
                        "span": {
                            "begin": 26,
                            "end": 30
                        }
                    }
                ],
                "frameName": "Finish_competition",
                "origin_lus": [
                    "katu .勝つ"
                ],
                "relations": [],
                "annotation_id": 0,
                "sent_id": 4607
            }
        }
    ],
    "frameID": 798,
    "en_lu": [
        "katu .勝つ"
    ],
    "ko_pos": "VV",
    "frameName": "Finish_competition"
}