{
    "ko_lu": "생각하다.v",
    "patterns": [
        {
            "valenceText": "annotation id: 17525",
            "examples": {
                "ko_annotation_id": 17525,
                "denotations": [
                    {
                        "obj": "opinion",
                        "span": {
                            "begin": 0,
                            "end": 69
                        },
                        "id": "2"
                    },
                    {
                        "obj": "cognizer",
                        "span": {
                            "begin": 72,
                            "end": 82
                        },
                        "id": "3"
                    },
                    {
                        "obj": "target",
                        "span": {
                            "begin": 87,
                            "end": 93
                        },
                        "id": "1"
                    }
                ],
                "frameName": "Opinion",
                "origin_lus": [
                    "thinking",
                    "felt"
                ],
                "relations": [
                    {
                        "pred": "",
                        "obj": "2",
                        "subj": "1"
                    },
                    {
                        "pred": "",
                        "obj": "3",
                        "subj": "1"
                    }
                ],
                "annotation_id": 5311,
                "sent_id": 1011
            }
        },
        {
            "valenceText": "annotation id: 17526",
            "examples": {
                "ko_annotation_id": 17526,
                "denotations": [
                    {
                        "obj": "cognizer",
                        "span": {
                            "begin": 43,
                            "end": 52
                        },
                        "id": "2"
                    },
                    {
                        "obj": "opinion",
                        "span": {
                            "begin": 85,
                            "end": 127
                        },
                        "id": "3"
                    },
                    {
                        "obj": "target",
                        "span": {
                            "begin": 121,
                            "end": 127
                        },
                        "id": "1"
                    }
                ],
                "frameName": "Opinion",
                "origin_lus": [
                    "thinking",
                    "felt"
                ],
                "relations": [
                    {
                        "pred": "",
                        "obj": "2",
                        "subj": "1"
                    },
                    {
                        "pred": "",
                        "obj": "3",
                        "subj": "1"
                    }
                ],
                "annotation_id": 5899,
                "sent_id": 1127
            }
        }
    ],
    "frameID": 1412,
    "en_lu": [
        "felt",
        "think"
    ],
    "ko_pos": "VV",
    "frameName": "Opinion"
}