{
    "frameName": "Experiencer_obj",
    "patterns": [
        {
            "valenceText": "annotation id: sejong.69989",
            "examples": [
                {
                    "frameName": "Experiencer_obj",
                    "denotations": [
                        {
                            "id": "1",
                            "span": {
                                "begin": 21,
                                "end": 26
                            },
                            "obj": "target"
                        }
                    ],
                    "text": "아버지는 우리집 개를 앞집 개와 서로 교미시켰다.",
                    "target": "교미시켰다",
                    "ko_annotation_id": "sejong.69989",
                    "relations": []
                }
            ]
        },
        {
            "valenceText": "annotation id: sejong.69990",
            "examples": [
                {
                    "frameName": "Experiencer_obj",
                    "denotations": [
                        {
                            "id": "1",
                            "span": {
                                "begin": 21,
                                "end": 26
                            },
                            "obj": "target"
                        }
                    ],
                    "text": "아버지는 우리집 개와 앞집 개를 서로 교미시켰다.",
                    "target": "교미시켰다",
                    "ko_annotation_id": "sejong.69990",
                    "relations": []
                }
            ]
        }
    ],
    "frameID": 47,
    "ko_pos": "VV",
    "ko_lu": "교미시키다.v.Experiencer_obj",
    "lu_id": 9239,
    "en_lus": [
        "shake.v.841"
    ]
}