{
    "en_lus": [
        "decide"
    ],
    "ko_pos": "VA",
    "frameName": "Choosing",
    "patterns": [
        {
            "examples": [
                {
                    "ko_annotation_id": 4570,
                    "frameName": "Choosing",
                    "text": "나의 집은 지주로 떠받쳐있기 때문에, Marin에 있는 집으로 가야 할지 나는 결정할 수 없었다.",
                    "sent_id": 131,
                    "annotation_id": 770,
                    "denotations": [
                        {
                            "span": {
                                "end": 39,
                                "begin": 21
                            },
                            "obj": "possibilities",
                            "id": "3"
                        },
                        {
                            "span": {
                                "end": 42,
                                "begin": 41
                            },
                            "obj": "cognizer",
                            "id": "2"
                        },
                        {
                            "span": {
                                "end": 47,
                                "begin": 44
                            },
                            "obj": "target",
                            "id": "1"
                        }
                    ],
                    "origin_lus": [
                        "decide"
                    ],
                    "relations": [
                        {
                            "obj": "2",
                            "subj": "1",
                            "pred": ""
                        },
                        {
                            "obj": "3",
                            "subj": "1",
                            "pred": ""
                        }
                    ]
                }
            ],
            "valenceText": "annotation id: 4570"
        }
    ],
    "ko_lu": "결정하다.a",
    "frameID": 352,
    "lu_id": 1431
}