{
    "frameName": "Judgment_direct_address",
    "patterns": [
        {
            "valenceText": "annotation id: sejong.83204",
            "examples": [
                {
                    "frameName": "Judgment_direct_address",
                    "denotations": [
                        {
                            "id": "1",
                            "span": {
                                "begin": 10,
                                "end": 15
                            },
                            "obj": "target"
                        }
                    ],
                    "text": "너무 심하게 말을 쏘아붙이지 마라.",
                    "target": "쏘아붙이지",
                    "ko_annotation_id": "sejong.83204",
                    "relations": []
                }
            ]
        },
        {
            "valenceText": "annotation id: sejong.83205",
            "examples": [
                {
                    "frameName": "Judgment_direct_address",
                    "denotations": [
                        {
                            "id": "1",
                            "span": {
                                "begin": 23,
                                "end": 28
                            },
                            "obj": "target"
                        }
                    ],
                    "text": "나는 그 친구에게 자꾸 헛소리하지 말라고 쏘아붙였다.",
                    "target": "쏘아붙였다",
                    "ko_annotation_id": "sejong.83205",
                    "relations": []
                }
            ]
        },
        {
            "valenceText": "annotation id: sejong.83203",
            "examples": [
                {
                    "frameName": "Judgment_direct_address",
                    "denotations": [
                        {
                            "id": "1",
                            "span": {
                                "begin": 17,
                                "end": 23
                            },
                            "obj": "target"
                        }
                    ],
                    "text": "친구에게 짜증을 내며 한 마디 쏘아붙였더니 마음이 영 불편하다.",
                    "target": "쏘아붙였더니",
                    "ko_annotation_id": "sejong.83203",
                    "relations": []
                }
            ]
        },
        {
            "valenceText": "annotation id: sejong.83206",
            "examples": [
                {
                    "frameName": "Judgment_direct_address",
                    "denotations": [
                        {
                            "id": "1",
                            "span": {
                                "begin": 19,
                                "end": 25
                            },
                            "obj": "target"
                        }
                    ],
                    "text": "친구에게 그만 좀 허세를 부리라고 쏘아붙였더니 그 녀석은 금새 풀이 죽었다.",
                    "target": "쏘아붙였더니",
                    "ko_annotation_id": "sejong.83206",
                    "relations": []
                }
            ]
        }
    ],
    "frameID": 711,
    "ko_pos": "VV",
    "ko_lu": "쏘아붙이다.v.Judgment_direct_address",
    "lu_id": 12337,
    "en_lus": [
        "upbraid.v.8944",
        "reproach.v.8966"
    ]
}