{
    "frameName": "Inspecting",
    "patterns": [
        {
            "valenceText": "annotation id: sejong.84209",
            "examples": [
                {
                    "frameName": "Inspecting",
                    "denotations": [
                        {
                            "id": "1",
                            "span": {
                                "begin": 3,
                                "end": 7
                            },
                            "obj": "target"
                        }
                    ],
                    "text": "아직 검시되지 않은 시신들은 낮은 기온에 보관하여 부패를 지연시켜야 한다.",
                    "target": "검시되지",
                    "ko_annotation_id": "sejong.84209",
                    "relations": []
                }
            ]
        }
    ],
    "frameID": 1262,
    "ko_pos": "VV",
    "ko_lu": "검시되다.v.Inspecting",
    "lu_id": 13142,
    "en_lus": [
        "frisk.v.11267",
        "examine.v.11271"
    ]
}