{
    "frameName": "Timespan",
    "patterns": [
        {
            "valenceText": "annotation id: 6310",
            "examples": [
                {
                    "frameName": "Timespan",
                    "denotations": [
                        {
                            "obj": "Duration",
                            "span": {
                                "begin": 30,
                                "end": 35
                            }
                        },
                        {
                            "obj": "Target",
                            "span": {
                                "begin": 36,
                                "end": 38
                            }
                        }
                    ],
                    "origin_lus": [
                        "aida .間 "
                    ],
                    "ko_annotation_id": 6310,
                    "text": "원이 개설되고부터, 명치 원년에 형장이 폐지되기까지, 이백여 년 동안에 매장된 사체는 20여만 구라 합니다.",
                    "sent_id": 4670,
                    "relations": [],
                    "annotation_id": 0
                }
            ]
        },
        {
            "valenceText": "annotation id: sejong.15725",
            "examples": [
                {
                    "frameName": "Timespan",
                    "denotations": [
                        {
                            "obj": "target",
                            "span": {
                                "begin": 14,
                                "end": 16
                            },
                            "id": "1"
                        }
                    ],
                    "text": "그는 자신의 얼굴이 너무 동안인 것이 불만이었다.",
                    "target": "동안",
                    "ko_annotation_id": "sejong.15725",
                    "relations": []
                }
            ]
        }
    ],
    "frameID": 2142,
    "ko_pos": "NNG",
    "ko_lu": "동안.n.Timespan",
    "lu_id": 2002,
    "en_lus": [
        "aida .間 "
    ]
}